drongo_core_modules-1.1.2.dist-info/METADATA
drongo_core_modules-1.1.2.dist-info/RECORD
drongo_core_modules-1.1.2.dist-info/WHEEL
drongo_core_modules-1.1.2.dist-info/top_level.txt
drongo_core_modules-1.1.2.dist-info/zip-safe
drongo_modules/__init__.py
drongo_modules/core/__init__.py
drongo_modules/core/auth/__init__.py
drongo_modules/core/auth/api.py
drongo_modules/core/auth/middleware.py
drongo_modules/core/auth/module.py
drongo_modules/core/auth/validators.py
drongo_modules/core/auth/backends/__init__.py
drongo_modules/core/auth/backends/_mongo/__init__.py
drongo_modules/core/auth/backends/_mongo/models.py
drongo_modules/core/auth/backends/_mongo/services.py
drongo_modules/core/auth/backends/_postgres/__init__.py
drongo_modules/core/auth/backends/_postgres/models.py
drongo_modules/core/auth/backends/_postgres/services.py
drongo_modules/core/database/__init__.py
drongo_modules/core/database/module.py
drongo_modules/core/database/databases/__init__.py
drongo_modules/core/database/databases/_mongo.py
drongo_modules/core/database/databases/_mysql.py
drongo_modules/core/database/databases/_postgres.py
drongo_modules/core/database/databases/_redis.py
drongo_modules/core/email/__init__.py
drongo_modules/core/email/module.py
drongo_modules/core/email/backends/__init__.py
drongo_modules/core/email/backends/_mailgun/__init__.py
drongo_modules/core/email/backends/_mailgun/services.py
drongo_modules/core/media/__init__.py
drongo_modules/core/media/api.py
drongo_modules/core/media/models.py
drongo_modules/core/media/module.py
drongo_modules/core/media/admin/__init__.py
drongo_modules/core/media/admin/api.py
drongo_modules/core/media/storage/__init__.py
drongo_modules/core/media/storage/_filesystem/__init__.py
drongo_modules/core/media/storage/_filesystem/services.py
drongo_modules/core/module/__init__.py
drongo_modules/core/module/get_path.py
drongo_modules/core/module/module.py
drongo_modules/tests/__init__.py
drongo_modules/tests/utils.py
drongo_modules/tests/core/__init__.py
drongo_modules/tests/core/auth/__init__.py
drongo_modules/tests/core/auth/mongo/__init__.py
drongo_modules/tests/core/auth/mongo/common.py
